{
  "getHealthInfo": {
    "result": "succ",
    "message": "",
    "data": {
      "cstmFnm": "정동현",
      "mmbrWegVl": "75",
      "mmbrMmtDvcd": "H",
      "gndrDvcd": "M"
    }
  },
  "getMyWater": {
    "result": "succ",
    "message": "",
    "data": {
      "today": {
        "intakeRecomm": "100",
        "waterAvg": "100",
        "gradePerTxt": "하위",
        "gradePer": "27",
        "gradeTxt": "운동량이 매우 매우 부족합니다.",
        "gradeTxtSub": "본인 건강을 위해서라도 열심히 걸으세요.",
        "grade": "46"
      },
      "graph": [
        {
          "xLabel": "11",
          "y1": 1412,
          "y2": 2000
        },
        {
          "xLabel": "12",
          "y1": 1123,
          "y2": 2000
        },
        {
          "xLabel": "01",
          "y1": 1242,
          "y2": 2000
        },
        {
          "xLabel": "02",
          "y1": 1345,
          "y2": 2000
        },
        {
          "xLabel": "03",
          "y1": 1251,
          "y2": 2000
        },
        {
          "xLabel": "04",
          "y1": 2345,
          "y2": 2000
        },
        {
          "xLabel": "05",
          "y1": 2341,
          "y2": 2000
        },
        {
          "xLabel": "06",
          "y1": 3222,
          "y2": 2000
        },
        {
          "xLabel": "07",
          "y1": 3231,
          "y2": 2000
        },
        {
          "xLabel": "08",
          "y1": 2314,
          "y2": 2000
        },
        {
          "xLabel": "09",
          "y1": 5234,
          "y2": 2000
        },
        {
          "xLabel": "10",
          "y1": 4512,
          "y2": 2000
        },
        {
          "xLabel": "11",
          "y1": 2318,
          "y2": 2000
        }
      ]
    }
  }
}